{
    "1": {
        "10": {
            "255": "28",
            "27": "27"
        },
        "11": {
            "1": "10"
        },
        "13": {
            "156": "11",
            "206": "12"
        },
        "14": {
            "15": "10",
            "93": "4"
        },
        "15": {
            "117": "28",
            "121": "28"
        },
        "16": {
            "152": "12",
            "174": "11"
        },
        "17": {
            "133": "10",
            "180": "27",
            "76": "27"
        },
        "18": {
            "137": "27",
            "228": "10",
            "56": "11"
        },
        "19": {
            "112": "12",
            "217": "10",
            "98": "10"
        },
        "20": {
            "32": "27",
            "72": "27",
            "79": "27"
        },
        "21": {
            "196": "28",
            "201": "12",
            "51": "8"
        },
        "22": {
            "212": "28",
            "238": "20",
            "38": "20"
        },
        "23": {
            "142": "20",
            "147": "12",
            "160": "20",
            "234": "11"
        },
        "24": {
            "128": "8",
            "43": "8",
            "6": "8",
            "61": "8"
        },
        "25": {
            "103": "20",
            "107": "28",
            "20": "20",
            "246": "28"
        },
        "26": {
            "190": "27",
            "241": "27",
            "251": "27",
            "67": "28"
        },
        "7": {
            "46": "4",
            "86": "4"
        },
        "8": {
            "165": "4",
            "186": "20"
        },
        "9": {
            "169": "11",
            "223": "11"
        }
    },
    "2": {
        "10": {
            "255": "9",
            "27": "18"
        },
        "11": {
            "1": "25"
        },
        "13": {
            "156": "30",
            "206": "22"
        },
        "14": {
            "15": "25",
            "93": "25"
        },
        "15": {
            "117": "15",
            "121": "15"
        },
        "16": {
            "152": "9",
            "174": "9"
        },
        "17": {
            "133": "14",
            "180": "14",
            "76": "14"
        },
        "18": {
            "137": "22",
            "228": "22",
            "56": "22"
        },
        "19": {
            "112": "18",
            "217": "22",
            "98": "18"
        },
        "20": {
            "32": "30",
            "72": "30",
            "79": "30"
        },
        "21": {
            "196": "15",
            "201": "16",
            "51": "16"
        },
        "22": {
            "212": "16",
            "238": "9",
            "38": "16"
        },
        "23": {
            "142": "16",
            "147": "30",
            "160": "16",
            "234": "30"
        },
        "24": {
            "128": "22",
            "43": "22",
            "6": "22",
            "61": "22"
        },
        "25": {
            "103": "16",
            "107": "22",
            "20": "9",
            "246": "22"
        },
        "26": {
            "190": "14",
            "241": "14",
            "251": "14",
            "67": "14"
        },
        "7": {
            "46": "18",
            "86": "15"
        },
        "8": {
            "165": "25",
            "186": "25"
        },
        "9": {
            "169": "15",
            "223": "25"
        }
    },
    "3": {
        "10": {
            "255": "1",
            "27": "1"
        },
        "11": {
            "1": "23"
        },
        "13": {
            "156": "1",
            "206": "21"
        },
        "14": {
            "15": "24",
            "93": "24"
        },
        "15": {
            "117": "24",
            "121": "24"
        },
        "16": {
            "152": "24",
            "174": "1"
        },
        "17": {
            "133": "23",
            "180": "24",
            "76": "23"
        },
        "18": {
            "137": "24",
            "228": "21",
            "56": "21"
        },
        "19": {
            "112": "21",
            "217": "21",
            "98": "21"
        },
        "20": {
            "32": "24",
            "72": "24",
            "79": "24"
        },
        "21": {
            "196": "1",
            "201": "1",
            "51": "1"
        },
        "22": {
            "212": "23",
            "238": "23",
            "38": "23"
        },
        "23": {
            "142": "21",
            "147": "0",
            "160": "0",
            "234": "21"
        },
        "24": {
            "128": "21",
            "43": "21",
            "6": "21",
            "61": "21"
        },
        "25": {
            "103": "0",
            "107": "24",
            "20": "24",
            "246": "0"
        },
        "26": {
            "190": "23",
            "241": "23",
            "251": "23",
            "67": "23"
        },
        "7": {
            "46": "23",
            "86": "23"
        },
        "8": {
            "165": "0",
            "186": "0"
        },
        "9": {
            "169": "0",
            "223": "0"
        }
    },
    "4": {
        "10": {
            "255": "7",
            "27": "7"
        },
        "12": {
            "21": "28"
        },
        "13": {
            "156": "7",
            "206": "2"
        },
        "14": {
            "87": "11",
            "93": "8"
        },
        "15": {
            "117": "28",
            "121": "28"
        },
        "16": {
            "152": "2",
            "174": "8"
        },
        "17": {
            "133": "8",
            "180": "8",
            "76": "8"
        },
        "18": {
            "138": "26",
            "228": "11",
            "56": "28"
        },
        "19": {
            "217": "28",
            "242": "8",
            "98": "8"
        },
        "20": {
            "113": "11",
            "32": "12",
            "72": "12"
        },
        "21": {
            "196": "17",
            "201": "26",
            "51": "12"
        },
        "22": {
            "212": "12",
            "238": "28",
            "38": "12"
        },
        "23": {
            "142": "17",
            "147": "17",
            "160": "12",
            "234": "12"
        },
        "24": {
            "128": "17",
            "165": "12",
            "43": "12",
            "6": "17"
        },
        "25": {
            "103": "7",
            "107": "7",
            "15": "17",
            "246": "17"
        },
        "26": {
            "190": "26",
            "2": "17",
            "251": "2",
            "67": "26"
        },
        "7": {
            "46": "26",
            "80": "26"
        },
        "8": {
            "186": "2",
            "62": "2"
        },
        "9": {
            "169": "11",
            "223": "11"
        }
    },
    "5": {
        "10": {
            "255": "25",
            "27": "25"
        },
        "12": {
            "21": "5"
        },
        "13": {
            "156": "22",
            "206": "22"
        },
        "14": {
            "87": "25",
            "93": "25"
        },
        "15": {
            "117": "20",
            "121": "20"
        },
        "16": {
            "152": "5",
            "174": "10"
        },
        "17": {
            "133": "29",
            "180": "10",
            "76": "29"
        },
        "18": {
            "138": "10",
            "228": "10",
            "56": "9"
        },
        "19": {
            "217": "29",
            "242": "29",
            "98": "29"
        },
        "20": {
            "113": "13",
            "32": "29",
            "72": "29"
        },
        "21": {
            "196": "25",
            "201": "29",
            "51": "25"
        },
        "22": {
            "212": "9",
            "238": "9",
            "38": "9"
        },
        "23": {
            "142": "22",
            "147": "20",
            "160": "20",
            "234": "22"
        },
        "24": {
            "128": "13",
            "165": "25",
            "43": "13",
            "6": "25"
        },
        "25": {
            "103": "9",
            "107": "20",
            "15": "9",
            "246": "9"
        },
        "26": {
            "190": "13",
            "2": "13",
            "251": "10",
            "67": "10"
        },
        "7": {
            "46": "22",
            "80": "5"
        },
        "8": {
            "186": "25",
            "62": "25"
        },
        "9": {
            "169": "5",
            "223": "20"
        }
    },
    "6": {
        "10": {
            "255": "1",
            "27": "1"
        },
        "12": {
            "21": "16"
        },
        "13": {
            "156": "3",
            "206": "3"
        },
        "14": {
            "87": "3",
            "93": "3"
        },
        "15": {
            "117": "1",
            "121": "1"
        },
        "16": {
            "152": "24",
            "174": "24"
        },
        "17": {
            "133": "3",
            "180": "3",
            "76": "3"
        },
        "18": {
            "138": "19",
            "228": "19",
            "56": "19"
        },
        "19": {
            "217": "3",
            "242": "3",
            "98": "3"
        },
        "20": {
            "113": "19",
            "32": "19",
            "72": "19"
        },
        "21": {
            "196": "1",
            "201": "1",
            "51": "1"
        },
        "22": {
            "212": "24",
            "238": "24",
            "38": "24"
        },
        "23": {
            "142": "16",
            "147": "16",
            "160": "16",
            "234": "16"
        },
        "24": {
            "128": "19",
            "165": "19",
            "43": "19",
            "6": "19"
        },
        "25": {
            "103": "1",
            "107": "24",
            "15": "24",
            "246": "24"
        },
        "26": {
            "190": "16",
            "2": "16",
            "251": "16",
            "67": "16"
        },
        "7": {
            "46": "16",
            "80": "1"
        },
        "8": {
            "186": "24",
            "62": "1"
        },
        "9": {
            "169": "16",
            "223": "16"
        }
    },
    "7": {
        "10": {
            "122": "30",
            "33": "30"
        },
        "12": {
            "21": "28",
            "7": "28"
        },
        "13": {
            "156": "21",
            "206": "21"
        },
        "14": {
            "191": "17",
            "93": "17"
        },
        "15": {
            "117": "23",
            "47": "23"
        },
        "16": {
            "152": "11",
            "174": "11"
        },
        "17": {
            "133": "7",
            "180": "7",
            "76": "7"
        },
        "18": {
            "138": "11",
            "228": "11",
            "57": "17"
        },
        "19": {
            "217": "23",
            "242": "23",
            "98": "23"
        },
        "20": {
            "113": "7",
            "72": "7"
        },
        "21": {
            "196": "21",
            "201": "21",
            "51": "21"
        },
        "22": {
            "212": "23",
            "238": "23",
            "38": "23"
        },
        "23": {
            "142": "30",
            "147": "30",
            "160": "30",
            "28": "7"
        },
        "24": {
            "128": "21",
            "165": "21",
            "235": "0",
            "43": "0"
        },
        "25": {
            "103": "11",
            "107": "11",
            "15": "11",
            "246": "11"
        },
        "26": {
            "2": "30",
            "251": "30",
            "67": "21",
            "88": "21"
        },
        "7": {
            "224": "0",
            "80": "0"
        },
        "8": {
            "186": "28",
            "62": "28"
        },
        "9": {
            "169": "28",
            "256": "28"
        }
    },
    "8": {
        "10": {
            "122": "26",
            "33": "2"
        },
        "12": {
            "21": "4",
            "7": "18"
        },
        "13": {
            "156": "4",
            "206": "4"
        },
        "14": {
            "191": "18",
            "93": "2"
        },
        "15": {
            "117": "5",
            "47": "5"
        },
        "16": {
            "152": "26",
            "174": "8"
        },
        "17": {
            "133": "10",
            "180": "10",
            "76": "10"
        },
        "18": {
            "138": "26",
            "228": "26",
            "57": "26"
        },
        "19": {
            "217": "18",
            "242": "18",
            "98": "2"
        },
        "20": {
            "113": "4",
            "72": "4"
        },
        "21": {
            "196": "26",
            "201": "26",
            "51": "26"
        },
        "22": {
            "212": "8",
            "238": "8",
            "38": "8"
        },
        "23": {
            "142": "10",
            "147": "10",
            "160": "10",
            "28": "10"
        },
        "24": {
            "128": "8",
            "165": "8",
            "235": "8",
            "43": "8"
        },
        "25": {
            "103": "5",
            "107": "10",
            "15": "5",
            "246": "10"
        },
        "26": {
            "2": "27",
            "251": "27",
            "67": "27",
            "88": "27"
        },
        "7": {
            "224": "2",
            "80": "2"
        },
        "8": {
            "186": "5",
            "62": "5"
        },
        "9": {
            "169": "27",
            "256": "27"
        }
    },
    "9": {
        "10": {
            "122": "3",
            "33": "3"
        },
        "12": {
            "21": "3",
            "7": "3"
        },
        "13": {
            "156": "29",
            "206": "29"
        },
        "14": {
            "191": "13",
            "93": "13"
        },
        "15": {
            "117": "29",
            "47": "29"
        },
        "16": {
            "152": "19",
            "174": "19"
        },
        "17": {
            "133": "29",
            "180": "29",
            "76": "29"
        },
        "18": {
            "138": "19",
            "228": "19",
            "57": "19"
        },
        "19": {
            "217": "19",
            "242": "19",
            "98": "19"
        },
        "20": {
            "113": "19",
            "72": "19"
        },
        "21": {
            "196": "13",
            "201": "13",
            "51": "13"
        },
        "22": {
            "212": "6",
            "238": "6",
            "38": "6"
        },
        "23": {
            "142": "29",
            "147": "29",
            "160": "6",
            "28": "29"
        },
        "24": {
            "128": "3",
            "165": "6",
            "235": "3",
            "43": "6"
        },
        "25": {
            "103": "13",
            "107": "13",
            "15": "13",
            "246": "13"
        },
        "26": {
            "2": "13",
            "251": "13",
            "67": "13",
            "88": "13"
        },
        "7": {
            "224": "6",
            "80": "6"
        },
        "8": {
            "186": "29",
            "62": "29"
        },
        "9": {
            "169": "3",
            "256": "3"
        }
    },
    "10": {
        "10": {
            "218": "12",
            "33": "12"
        },
        "12": {
            "21": "11",
            "7": "11"
        },
        "13": {
            "156": "11",
            "206": "11"
        },
        "14": {
            "202": "16"
        },
        "15": {
            "117": "25",
            "47": "25"
        },
        "16": {
            "152": "11",
            "175": "11"
        },
        "17": {
            "133": "14",
            "242": "14",
            "76": "14"
        },
        "18": {
            "138": "7",
            "228": "7",
            "57": "7"
        },
        "19": {
            "123": "7",
            "94": "7",
            "98": "7"
        },
        "20": {
            "113": "25",
            "73": "28",
            "89": "25"
        },
        "21": {
            "196": "15",
            "51": "15",
            "81": "15"
        },
        "22": {
            "212": "28",
            "238": "25",
            "38": "28"
        },
        "23": {
            "142": "25",
            "147": "25",
            "247": "25",
            "28": "25"
        },
        "24": {
            "128": "11",
            "161": "15",
            "235": "15",
            "43": "11"
        },
        "25": {
            "103": "16",
            "107": "16",
            "15": "16",
            "166": "16"
        },
        "26": {
            "181": "28",
            "2": "28",
            "251": "28",
            "67": "28"
        },
        "7": {
            "192": "14",
            "224": "14"
        },
        "8": {
            "186": "14",
            "62": "14"
        },
        "9": {
            "169": "12",
            "256": "12"
        }
    },
    "11": {
        "10": {
            "218": "22",
            "33": "22"
        },
        "12": {
            "21": "4",
            "7": "4"
        },
        "13": {
            "156": "2",
            "206": "4"
        },
        "14": {
            "202": "30"
        },
        "15": {
            "117": "8",
            "47": "8"
        },
        "16": {
            "152": "8",
            "175": "8"
        },
        "17": {
            "133": "17",
            "242": "17",
            "76": "17"
        },
        "18": {
            "138": "8",
            "228": "4",
            "57": "4"
        },
        "19": {
            "123": "18",
            "94": "8",
            "98": "18"
        },
        "20": {
            "113": "2",
            "73": "2",
            "89": "2"
        },
        "21": {
            "196": "22",
            "51": "22",
            "81": "22"
        },
        "22": {
            "212": "18",
            "238": "18",
            "38": "18"
        },
        "23": {
            "142": "30",
            "147": "30",
            "247": "30",
            "28": "30"
        },
        "24": {
            "128": "17",
            "161": "18",
            "235": "18",
            "43": "17"
        },
        "25": {
            "103": "17",
            "107": "17",
            "15": "17",
            "166": "17"
        },
        "26": {
            "181": "27",
            "2": "30",
            "251": "30",
            "67": "30"
        },
        "7": {
            "192": "27",
            "224": "27"
        },
        "8": {
            "186": "2",
            "62": "2"
        },
        "9": {
            "169": "30",
            "256": "30"
        }
    },
    "12": {
        "10": {
            "218": "1",
            "33": "1"
        },
        "12": {
            "21": "3",
            "7": "3"
        },
        "13": {
            "156": "29",
            "206": "29"
        },
        "14": {
            "202": "6"
        },
        "15": {
            "117": "29",
            "47": "29"
        },
        "16": {
            "152": "6",
            "175": "6"
        },
        "17": {
            "133": "29",
            "242": "29",
            "76": "29"
        },
        "18": {
            "138": "19",
            "228": "19",
            "57": "19"
        },
        "19": {
            "123": "29",
            "94": "29",
            "98": "3"
        },
        "20": {
            "113": "19",
            "73": "19",
            "89": "1"
        },
        "21": {
            "196": "6",
            "51": "6",
            "81": "6"
        },
        "22": {
            "212": "3",
            "238": "3",
            "38": "6"
        },
        "23": {
            "142": "19",
            "147": "3",
            "247": "19",
            "28": "3"
        },
        "24": {
            "128": "3",
            "161": "3",
            "235": "6",
            "43": "6"
        },
        "25": {
            "103": "1",
            "107": "6",
            "15": "1",
            "166": "6"
        },
        "26": {
            "181": "1",
            "2": "1",
            "251": "1",
            "67": "1"
        },
        "7": {
            "192": "19",
            "224": "3"
        },
        "8": {
            "186": "29",
            "62": "29"
        },
        "9": {
            "169": "19",
            "256": "19"
        }
    },
    "13": {
        "10": {
            "176": "15"
        },
        "11": {
            "52": "15",
            "8": "15"
        },
        "12": {
            "21": "14",
            "229": "14"
        },
        "13": {
            "202": "9",
            "218": "9"
        },
        "14": {
            "170": "24",
            "3": "24"
        },
        "15": {
            "117": "24",
            "47": "24"
        },
        "16": {
            "152": "11",
            "43": "11"
        },
        "17": {
            "16": "24",
            "242": "24",
            "76": "24"
        },
        "18": {
            "138": "25",
            "57": "13",
            "94": "13"
        },
        "19": {
            "123": "25",
            "134": "25",
            "98": "25"
        },
        "20": {
            "113": "25",
            "73": "25",
            "89": "25"
        },
        "21": {
            "197": "13",
            "207": "13",
            "81": "25"
        },
        "22": {
            "212": "23",
            "238": "23",
            "38": "23"
        },
        "23": {
            "142": "15",
            "147": "15",
            "28": "15",
            "34": "24"
        },
        "24": {
            "128": "13",
            "157": "14",
            "161": "14",
            "235": "13"
        },
        "25": {
            "103": "11",
            "107": "11",
            "166": "11",
            "247": "11"
        },
        "26": {
            "181": "9",
            "251": "9",
            "67": "9"
        },
        "7": {
            "192": "23",
            "224": "23"
        },
        "8": {
            "186": "23",
            "62": "23"
        },
        "9": {
            "256": "14"
        }
    },
    "14": {
        "10": {
            "176": "20"
        },
        "11": {
            "52": "28",
            "8": "17"
        },
        "12": {
            "21": "16",
            "229": "16"
        },
        "13": {
            "202": "7",
            "218": "7"
        },
        "14": {
            "170": "26",
            "3": "26"
        },
        "15": {
            "117": "5",
            "47": "5"
        },
        "16": {
            "152": "28",
            "43": "28"
        },
        "17": {
            "16": "20",
            "242": "20",
            "76": "20"
        },
        "18": {
            "138": "7",
            "57": "7",
            "94": "7"
        },
        "19": {
            "123": "7",
            "134": "12",
            "98": "7"
        },
        "20": {
            "113": "17",
            "73": "17",
            "89": "17"
        },
        "21": {
            "197": "12",
            "207": "12",
            "81": "12"
        },
        "22": {
            "212": "20",
            "238": "20",
            "38": "20"
        },
        "23": {
            "142": "17",
            "147": "17",
            "28": "17",
            "34": "17"
        },
        "24": {
            "128": "26",
            "157": "26",
            "161": "26",
            "235": "26"
        },
        "25": {
            "103": "5",
            "107": "16",
            "166": "16",
            "247": "5"
        },
        "26": {
            "181": "28",
            "251": "28",
            "67": "28"
        },
        "7": {
            "192": "16",
            "224": "16"
        },
        "8": {
            "186": "5",
            "62": "5"
        },
        "9": {
            "256": "12"
        }
    },
    "15": {
        "10": {
            "176": "19"
        },
        "11": {
            "52": "2",
            "8": "2"
        },
        "12": {
            "21": "3",
            "229": "3"
        },
        "13": {
            "202": "6",
            "218": "6"
        },
        "14": {
            "170": "27",
            "3": "27"
        },
        "15": {
            "117": "19",
            "47": "19"
        },
        "16": {
            "152": "3",
            "43": "3"
        },
        "17": {
            "16": "3",
            "242": "27",
            "76": "27"
        },
        "18": {
            "138": "19",
            "57": "19",
            "94": "19"
        },
        "19": {
            "123": "2",
            "134": "19",
            "98": "2"
        },
        "20": {
            "113": "19",
            "73": "19",
            "89": "19"
        },
        "21": {
            "197": "27",
            "207": "6",
            "81": "27"
        },
        "22": {
            "212": "3",
            "238": "3",
            "38": "3"
        },
        "23": {
            "142": "2",
            "147": "2",
            "28": "2",
            "34": "3"
        },
        "24": {
            "128": "6",
            "157": "6",
            "161": "6",
            "235": "6"
        },
        "25": {
            "103": "6",
            "107": "6",
            "166": "6",
            "247": "6"
        },
        "26": {
            "181": "27",
            "251": "27",
            "67": "27"
        },
        "7": {
            "192": "27",
            "224": "27"
        },
        "8": {
            "186": "27",
            "62": "2"
        },
        "9": {
            "256": "2"
        }
    },
    "16": {
        "10": {
            "108": "4",
            "58": "25"
        },
        "11": {
            "8": "14",
            "89": "14"
        },
        "12": {
            "118": "13",
            "252": "13"
        },
        "13": {
            "202": "13",
            "218": "13"
        },
        "14": {
            "29": "14",
            "3": "14"
        },
        "15": {
            "139": "8",
            "47": "8"
        },
        "16": {
            "114": "8",
            "239": "24"
        },
        "17": {
            "148": "14",
            "16": "14",
            "242": "14"
        },
        "18": {
            "187": "25",
            "82": "25",
            "94": "25"
        },
        "19": {
            "123": "14",
            "134": "14",
            "208": "14"
        },
        "20": {
            "22": "18",
            "39": "11",
            "73": "18"
        },
        "21": {
            "162": "18"
        },
        "22": {
            "225": "18",
            "256": "18"
        },
        "23": {
            "176": "24",
            "34": "18",
            "53": "18",
            "63": "24"
        },
        "24": {
            "157": "18",
            "235": "18",
            "68": "24",
            "99": "24"
        },
        "25": {
            "153": "8",
            "166": "8",
            "247": "8"
        },
        "26": {
            "104": "8",
            "181": "11",
            "213": "11",
            "77": "11"
        },
        "3": {
            "129": "25"
        },
        "5": {
            "171": "4"
        },
        "6": {
            "44": "4"
        },
        "7": {
            "192": "25",
            "197": "25"
        },
        "8": {
            "143": "13",
            "230": "13"
        }
    },
    "17": {
        "10": {
            "108": "0",
            "58": "22"
        },
        "11": {
            "8": "21",
            "89": "21"
        },
        "12": {
            "118": "21",
            "252": "21"
        },
        "13": {
            "202": "21",
            "218": "21"
        },
        "14": {
            "29": "29",
            "3": "29"
        },
        "15": {
            "139": "29",
            "47": "0"
        },
        "16": {
            "114": "26",
            "239": "26"
        },
        "17": {
            "148": "23",
            "16": "23",
            "242": "23"
        },
        "18": {
            "187": "26",
            "82": "23",
            "94": "23"
        },
        "19": {
            "123": "22",
            "134": "22",
            "208": "22"
        },
        "20": {
            "22": "0",
            "39": "0",
            "73": "0"
        },
        "21": {
            "162": "15"
        },
        "22": {
            "225": "26",
            "256": "26"
        },
        "23": {
            "176": "26",
            "34": "26",
            "53": "26",
            "63": "26"
        },
        "24": {
            "157": "22",
            "235": "15",
            "68": "22",
            "99": "22"
        },
        "25": {
            "153": "15",
            "166": "15",
            "247": "15"
        },
        "26": {
            "104": "21",
            "181": "15",
            "213": "21",
            "77": "15"
        },
        "3": {
            "129": "5"
        },
        "5": {
            "171": "29"
        },
        "6": {
            "44": "5"
        },
        "7": {
            "192": "23",
            "197": "23"
        },
        "8": {
            "143": "22",
            "230": "29"
        }
    },
    "18": {
        "10": {
            "108": "17",
            "58": "17"
        },
        "11": {
            "8": "1",
            "89": "1"
        },
        "12": {
            "118": "28",
            "252": "28"
        },
        "13": {
            "202": "17",
            "218": "17"
        },
        "14": {
            "29": "28",
            "3": "28"
        },
        "15": {
            "139": "12",
            "47": "12"
        },
        "16": {
            "114": "17",
            "239": "17"
        },
        "17": {
            "148": "1",
            "16": "3",
            "242": "3"
        },
        "18": {
            "187": "28",
            "82": "28",
            "94": "28"
        },
        "19": {
            "123": "12",
            "134": "12",
            "208": "12"
        },
        "20": {
            "22": "17",
            "39": "17",
            "73": "17"
        },
        "21": {
            "162": "1"
        },
        "22": {
            "225": "3",
            "256": "3"
        },
        "23": {
            "176": "3",
            "34": "3",
            "53": "3",
            "63": "3"
        },
        "24": {
            "157": "12",
            "235": "12",
            "68": "12",
            "99": "12"
        },
        "25": {
            "153": "12",
            "166": "12",
            "247": "12"
        },
        "26": {
            "104": "17",
            "181": "17",
            "213": "17",
            "77": "17"
        },
        "3": {
            "129": "17"
        },
        "5": {
            "171": "28"
        },
        "6": {
            "44": "1"
        },
        "7": {
            "192": "28",
            "197": "3"
        },
        "8": {
            "143": "1",
            "230": "1"
        }
    },
    "19": {
        "10": {
            "108": "27",
            "58": "27"
        },
        "12": {
            "105": "11",
            "118": "11"
        },
        "13": {
            "218": "14",
            "23": "14"
        },
        "14": {
            "29": "2",
            "3": "2"
        },
        "15": {
            "139": "27"
        },
        "16": {
            "114": "27",
            "239": "27"
        },
        "17": {
            "16": "6",
            "48": "6",
            "9": "6"
        },
        "18": {
            "187": "30",
            "82": "30",
            "94": "30"
        },
        "19": {
            "123": "11",
            "134": "6",
            "74": "2"
        },
        "20": {
            "203": "2",
            "39": "14"
        },
        "21": {
            "162": "19",
            "177": "4",
            "90": "19"
        },
        "22": {
            "100": "14",
            "158": "14",
            "256": "14"
        },
        "23": {
            "209": "11",
            "34": "11",
            "54": "19",
            "63": "4"
        },
        "24": {
            "130": "19",
            "225": "19",
            "235": "4",
            "68": "4"
        },
        "25": {
            "153": "19",
            "166": "19",
            "247": "2"
        },
        "26": {
            "149": "14",
            "181": "30",
            "213": "6",
            "77": "30"
        },
        "5": {
            "171": "27"
        },
        "6": {
            "44": "6"
        },
        "7": {
            "197": "27",
            "252": "11"
        },
        "8": {
            "143": "30",
            "230": "30"
        },
        "9": {
            "193": "27",
            "243": "30"
        }
    },
    "20": {
        "10": {
            "108": "7",
            "58": "7"
        },
        "12": {
            "105": "26",
            "118": "26"
        },
        "13": {
            "218": "10",
            "23": "10"
        },
        "14": {
            "29": "13",
            "3": "13"
        },
        "15": {
            "139": "5"
        },
        "16": {
            "114": "26",
            "239": "26"
        },
        "17": {
            "16": "5",
            "48": "5",
            "9": "29"
        },
        "18": {
            "187": "13",
            "82": "13",
            "94": "13"
        },
        "19": {
            "123": "7",
            "134": "7",
            "74": "7"
        },
        "20": {
            "203": "26",
            "39": "26"
        },
        "21": {
            "162": "29",
            "177": "21",
            "90": "29"
        },
        "22": {
            "100": "10",
            "158": "21",
            "256": "10"
        },
        "23": {
            "209": "13",
            "34": "13",
            "54": "7",
            "63": "21"
        },
        "24": {
            "130": "26",
            "225": "26",
            "235": "0",
            "68": "0"
        },
        "25": {
            "153": "0",
            "166": "21",
            "247": "21"
        },
        "26": {
            "149": "29",
            "181": "26",
            "213": "26",
            "77": "29"
        },
        "5": {
            "171": "26"
        },
        "6": {
            "44": "21"
        },
        "7": {
            "197": "7",
            "252": "7"
        },
        "8": {
            "143": "10",
            "230": "10"
        },
        "9": {
            "193": "0",
            "243": "5"
        }
    },
    "21": {
        "10": {
            "108": "15",
            "58": "15"
        },
        "12": {
            "105": "15",
            "118": "15"
        },
        "13": {
            "218": "28",
            "23": "28"
        },
        "14": {
            "29": "28",
            "3": "28"
        },
        "15": {
            "139": "15"
        },
        "16": {
            "114": "8",
            "239": "8"
        },
        "17": {
            "16": "3",
            "48": "3",
            "9": "1"
        },
        "18": {
            "187": "28",
            "82": "28",
            "94": "28"
        },
        "19": {
            "123": "15",
            "134": "15",
            "74": "15"
        },
        "20": {
            "203": "1",
            "39": "3"
        },
        "21": {
            "162": "28",
            "177": "28",
            "90": "28"
        },
        "22": {
            "100": "1",
            "158": "1",
            "256": "1"
        },
        "23": {
            "209": "3",
            "34": "3",
            "54": "3",
            "63": "3"
        },
        "24": {
            "130": "8",
            "225": "8",
            "235": "8",
            "68": "8"
        },
        "25": {
            "153": "28",
            "166": "28",
            "247": "28"
        },
        "26": {
            "149": "8",
            "181": "8",
            "213": "8",
            "77": "8"
        },
        "5": {
            "171": "1"
        },
        "6": {
            "44": "3"
        },
        "7": {
            "197": "3",
            "252": "1"
        },
        "8": {
            "143": "1",
            "230": "15"
        },
        "9": {
            "193": "15",
            "243": "15"
        }
    },
    "22": {
        "10": {
            "108": "16",
            "58": "16"
        },
        "12": {
            "105": "24",
            "172": "24"
        },
        "13": {
            "218": "16",
            "23": "16"
        },
        "14": {
            "236": "6",
            "29": "6"
        },
        "15": {
            "139": "16",
            "39": "16"
        },
        "16": {
            "114": "18",
            "239": "18"
        },
        "17": {
            "48": "30",
            "83": "19",
            "9": "30"
        },
        "18": {
            "188": "24",
            "94": "24"
        },
        "19": {
            "134": "23",
            "182": "23",
            "74": "23"
        },
        "20": {
            "17": "24",
            "203": "18",
            "4": "18"
        },
        "21": {
            "162": "20",
            "177": "20",
            "90": "20"
        },
        "22": {
            "100": "23",
            "119": "18",
            "158": "18"
        },
        "23": {
            "209": "6",
            "54": "6",
            "63": "6",
            "69": "20"
        },
        "24": {
            "130": "30",
            "225": "19",
            "257": "19",
            "44": "30"
        },
        "25": {
            "153": "6",
            "166": "6",
            "247": "6"
        },
        "26": {
            "124": "24",
            "149": "24",
            "198": "30",
            "77": "30"
        },
        "5": {
            "35": "16"
        },
        "7": {
            "214": "19",
            "252": "19"
        },
        "8": {
            "143": "23",
            "230": "23"
        },
        "9": {
            "193": "30",
            "243": "30"
        }
    },
    "23": {
        "10": {
            "108": "10",
            "58": "10"
        },
        "12": {
            "105": "26",
            "172": "26"
        },
        "13": {
            "218": "25",
            "23": "25"
        },
        "14": {
            "236": "25",
            "29": "25"
        },
        "15": {
            "139": "25",
            "39": "5"
        },
        "16": {
            "114": "9",
            "239": "9"
        },
        "17": {
            "48": "9",
            "83": "9",
            "9": "9"
        },
        "18": {
            "188": "14",
            "94": "14"
        },
        "19": {
            "134": "17",
            "182": "17",
            "74": "17"
        },
        "20": {
            "17": "25",
            "203": "25",
            "4": "17"
        },
        "21": {
            "162": "5",
            "177": "5",
            "90": "25"
        },
        "22": {
            "100": "26",
            "119": "14",
            "158": "14"
        },
        "23": {
            "209": "9",
            "54": "21",
            "63": "21",
            "69": "21"
        },
        "24": {
            "130": "10",
            "225": "10",
            "257": "14",
            "44": "10"
        },
        "25": {
            "153": "21",
            "166": "21",
            "247": "21"
        },
        "26": {
            "124": "21",
            "149": "21",
            "198": "17",
            "77": "17"
        },
        "5": {
            "35": "10"
        },
        "7": {
            "214": "5",
            "252": "5"
        },
        "8": {
            "143": "26",
            "230": "5"
        },
        "9": {
            "193": "26",
            "243": "26"
        }
    },
    "24": {
        "10": {
            "108": "12",
            "58": "12"
        },
        "12": {
            "105": "13",
            "172": "13"
        },
        "13": {
            "218": "12",
            "23": "12"
        },
        "14": {
            "236": "29",
            "29": "29"
        },
        "15": {
            "139": "0",
            "39": "0"
        },
        "16": {
            "114": "8",
            "239": "8"
        },
        "17": {
            "48": "13",
            "83": "13",
            "9": "13"
        },
        "18": {
            "188": "8",
            "94": "8"
        },
        "19": {
            "134": "8",
            "182": "8",
            "74": "8"
        },
        "20": {
            "17": "29",
            "203": "29",
            "4": "29"
        },
        "21": {
            "162": "0",
            "177": "29",
            "90": "29"
        },
        "22": {
            "100": "13",
            "119": "13",
            "158": "13"
        },
        "23": {
            "209": "0",
            "54": "0",
            "63": "0",
            "69": "0"
        },
        "24": {
            "130": "29",
            "225": "29",
            "257": "29",
            "44": "29"
        },
        "25": {
            "153": "12",
            "166": "12",
            "247": "12"
        },
        "26": {
            "124": "12",
            "149": "12",
            "198": "12",
            "77": "12"
        },
        "5": {
            "35": "12"
        },
        "7": {
            "214": "8",
            "252": "8"
        },
        "8": {
            "143": "13",
            "230": "13"
        },
        "9": {
            "193": "13",
            "243": "13"
        }
    },
    "25": {
        "10": {
            "24": "15",
            "40": "15"
        },
        "11": {
            "248": "30"
        },
        "12": {
            "172": "19"
        },
        "13": {
            "183": "4"
        },
        "14": {
            "236": "24",
            "29": "24"
        },
        "15": {
            "139": "2",
            "64": "2"
        },
        "16": {
            "114": "24",
            "239": "24"
        },
        "17": {
            "226": "19",
            "48": "6",
            "83": "15"
        },
        "18": {
            "131": "1",
            "188": "1",
            "219": "1"
        },
        "19": {
            "100": "4",
            "134": "6",
            "74": "4"
        },
        "20": {
            "17": "24",
            "203": "6",
            "4": "30"
        },
        "21": {
            "162": "15",
            "177": "15",
            "90": "15"
        },
        "22": {
            "119": "19",
            "158": "1",
            "167": "19"
        },
        "23": {
            "209": "6",
            "215": "6",
            "54": "6",
            "69": "6"
        },
        "24": {
            "257": "19",
            "44": "19",
            "95": "19"
        },
        "25": {
            "10": "1",
            "105": "24",
            "154": "24",
            "59": "24"
        },
        "26": {
            "124": "24",
            "149": "24",
            "198": "24",
            "77": "24"
        },
        "5": {
            "35": "2"
        },
        "6": {
            "109": "30"
        },
        "7": {
            "252": "4"
        },
        "8": {
            "144": "30",
            "230": "30"
        },
        "9": {
            "193": "15",
            "243": "15"
        }
    },
    "26": {
        "10": {
            "24": "9",
            "40": "9"
        },
        "11": {
            "248": "27"
        },
        "12": {
            "172": "23"
        },
        "13": {
            "183": "23"
        },
        "14": {
            "236": "17",
            "29": "17"
        },
        "15": {
            "139": "20",
            "64": "9"
        },
        "16": {
            "114": "7",
            "239": "7"
        },
        "17": {
            "226": "20",
            "48": "20",
            "83": "20"
        },
        "18": {
            "131": "27",
            "188": "27",
            "219": "27"
        },
        "19": {
            "100": "25",
            "134": "25",
            "74": "25"
        },
        "20": {
            "17": "7",
            "203": "7",
            "4": "7"
        },
        "21": {
            "162": "20",
            "177": "20",
            "90": "20"
        },
        "22": {
            "119": "7",
            "158": "7",
            "167": "27"
        },
        "23": {
            "209": "16",
            "215": "25",
            "54": "25",
            "69": "16"
        },
        "24": {
            "257": "17",
            "44": "17",
            "95": "17"
        },
        "25": {
            "10": "17",
            "105": "23",
            "154": "23",
            "59": "23"
        },
        "26": {
            "124": "16",
            "149": "16",
            "198": "16",
            "77": "16"
        },
        "5": {
            "35": "16"
        },
        "6": {
            "109": "25"
        },
        "7": {
            "252": "7"
        },
        "8": {
            "144": "9",
            "230": "16"
        },
        "9": {
            "193": "20",
            "243": "20"
        }
    },
    "27": {
        "10": {
            "24": "18",
            "40": "18"
        },
        "11": {
            "248": "18"
        },
        "12": {
            "172": "18"
        },
        "13": {
            "183": "8"
        },
        "14": {
            "236": "18",
            "29": "18"
        },
        "15": {
            "139": "0",
            "64": "0"
        },
        "16": {
            "114": "18",
            "239": "18"
        },
        "17": {
            "226": "0",
            "48": "0",
            "83": "29"
        },
        "18": {
            "131": "18",
            "188": "18",
            "219": "18"
        },
        "19": {
            "100": "3",
            "134": "3",
            "74": "3"
        },
        "20": {
            "17": "29",
            "203": "29",
            "4": "29"
        },
        "21": {
            "162": "29",
            "177": "29",
            "90": "29"
        },
        "22": {
            "119": "8",
            "158": "8",
            "167": "8"
        },
        "23": {
            "209": "0",
            "215": "0",
            "54": "0",
            "69": "0"
        },
        "24": {
            "257": "29",
            "44": "29",
            "95": "8"
        },
        "25": {
            "10": "29",
            "105": "29",
            "154": "29",
            "59": "29"
        },
        "26": {
            "124": "8",
            "149": "8",
            "198": "8",
            "77": "8"
        },
        "5": {
            "35": "8"
        },
        "6": {
            "109": "18"
        },
        "7": {
            "252": "3"
        },
        "8": {
            "144": "3",
            "230": "3"
        },
        "9": {
            "193": "3",
            "243": "3"
        }
    },
    "28": {
        "10": {
            "24": "24"
        },
        "11": {
            "220": "2",
            "248": "2"
        },
        "12": {
            "258": "4"
        },
        "13": {
            "183": "24",
            "253": "24"
        },
        "14": {
            "236": "26",
            "29": "6"
        },
        "15": {
            "139": "5",
            "64": "21"
        },
        "16": {
            "193": "26",
            "244": "26"
        },
        "17": {
            "210": "21",
            "226": "21",
            "83": "21"
        },
        "18": {
            "131": "6",
            "188": "6"
        },
        "19": {
            "100": "6",
            "74": "6"
        },
        "20": {
            "203": "24",
            "4": "26",
            "41": "26"
        },
        "21": {
            "162": "26",
            "177": "26",
            "96": "4"
        },
        "22": {
            "119": "4",
            "158": "4",
            "167": "4"
        },
        "23": {
            "215": "2",
            "231": "21",
            "54": "21",
            "69": "21"
        },
        "24": {
            "106": "5",
            "144": "6",
            "44": "6",
            "49": "6"
        },
        "25": {
            "10": "6",
            "154": "26",
            "59": "6",
            "91": "26"
        },
        "26": {
            "135": "24",
            "149": "24",
            "198": "24",
            "240": "24"
        },
        "5": {
            "35": "5"
        },
        "6": {
            "109": "21"
        },
        "7": {
            "115": "14",
            "125": "14"
        },
        "8": {
            "172": "5",
            "18": "5"
        },
        "9": {
            "78": "14"
        }
    },
    "29": {
        "10": {
            "24": "19"
        },
        "11": {
            "220": "15",
            "248": "11"
        },
        "12": {
            "258": "11"
        },
        "13": {
            "183": "27",
            "253": "19"
        },
        "14": {
            "236": "15",
            "29": "15"
        },
        "15": {
            "139": "15",
            "64": "19"
        },
        "16": {
            "193": "9",
            "244": "9"
        },
        "17": {
            "210": "19",
            "226": "19",
            "83": "19"
        },
        "18": {
            "131": "27",
            "188": "27"
        },
        "19": {
            "100": "30",
            "74": "30"
        },
        "20": {
            "203": "10",
            "4": "10",
            "41": "10"
        },
        "21": {
            "162": "15",
            "177": "15",
            "96": "15"
        },
        "22": {
            "119": "19",
            "158": "19",
            "167": "19"
        },
        "23": {
            "215": "9",
            "231": "10",
            "54": "9",
            "69": "10"
        },
        "24": {
            "106": "27",
            "144": "27",
            "44": "27",
            "49": "30"
        },
        "25": {
            "10": "10",
            "154": "10",
            "59": "10",
            "91": "30"
        },
        "26": {
            "135": "9",
            "149": "16",
            "198": "9",
            "240": "16"
        },
        "5": {
            "35": "16"
        },
        "6": {
            "109": "27"
        },
        "7": {
            "115": "16",
            "125": "16"
        },
        "8": {
            "172": "30",
            "18": "30"
        },
        "9": {
            "78": "11"
        }
    },
    "30": {
        "10": {
            "24": "12"
        },
        "11": {
            "220": "1",
            "248": "7"
        },
        "12": {
            "258": "12"
        },
        "13": {
            "183": "12",
            "253": "12"
        },
        "14": {
            "236": "25",
            "29": "25"
        },
        "15": {
            "139": "20",
            "64": "20"
        },
        "16": {
            "193": "12",
            "244": "12"
        },
        "17": {
            "210": "20",
            "226": "20",
            "83": "20"
        },
        "18": {
            "131": "1",
            "188": "1"
        },
        "19": {
            "100": "25",
            "74": "25"
        },
        "20": {
            "203": "7",
            "4": "7",
            "41": "7"
        },
        "21": {
            "162": "1",
            "177": "1",
            "96": "1"
        },
        "22": {
            "119": "20",
            "158": "20",
            "167": "20"
        },
        "23": {
            "215": "7",
            "231": "7",
            "54": "7",
            "69": "7"
        },
        "24": {
            "106": "25",
            "144": "25",
            "44": "25",
            "49": "25"
        },
        "25": {
            "10": "20",
            "154": "20",
            "59": "20",
            "91": "20"
        },
        "26": {
            "135": "12",
            "149": "12",
            "198": "12",
            "240": "12"
        },
        "5": {
            "35": "1"
        },
        "6": {
            "109": "1"
        },
        "7": {
            "115": "7",
            "125": "7"
        },
        "8": {
            "172": "25",
            "18": "25"
        },
        "9": {
            "78": "1"
        }
    },
    "31": {
        "10": {
            "5": "28",
            "65": "28"
        },
        "11": {
            "220": "0",
            "248": "0"
        },
        "12": {
            "150": "0",
            "258": "13"
        },
        "13": {
            "183": "24",
            "253": "24"
        },
        "14": {
            "140": "28",
            "236": "28"
        },
        "15": {
            "232": "3",
            "25": "3"
        },
        "16": {
            "244": "28"
        },
        "17": {
            "194": "13",
            "210": "24",
            "83": "13"
        },
        "18": {
            "131": "28",
            "188": "28",
            "45": "28"
        },
        "19": {
            "100": "4",
            "74": "4"
        },
        "20": {
            "203": "24",
            "36": "24",
            "41": "24"
        },
        "21": {
            "96": "4"
        },
        "22": {
            "119": "4",
            "158": "4",
            "167": "4"
        },
        "23": {
            "215": "0",
            "49": "6",
            "54": "6",
            "69": "0"
        },
        "24": {
            "106": "2",
            "11": "6",
            "144": "2",
            "30": "6"
        },
        "25": {
            "110": "2",
            "154": "24",
            "59": "2",
            "91": "2"
        },
        "26": {
            "135": "24",
            "163": "24",
            "198": "24",
            "240": "24"
        },
        "5": {
            "178": "2"
        },
        "7": {
            "115": "13",
            "125": "13"
        },
        "8": {
            "172": "3",
            "18": "3"
        },
        "9": {
            "226": "0",
            "78": "6"
        }
    },
    "32": {
        "10": {
            "5": "30",
            "65": "19"
        },
        "11": {
            "220": "21",
            "248": "21"
        },
        "12": {
            "150": "30",
            "258": "26"
        },
        "13": {
            "183": "30",
            "253": "30"
        },
        "14": {
            "140": "23",
            "236": "23"
        },
        "15": {
            "232": "26",
            "25": "22"
        },
        "16": {
            "244": "22"
        },
        "17": {
            "194": "22",
            "210": "19",
            "83": "19"
        },
        "18": {
            "131": "18",
            "188": "18",
            "45": "18"
        },
        "19": {
            "100": "23",
            "74": "23"
        },
        "20": {
            "203": "18",
            "36": "18",
            "41": "18"
        },
        "21": {
            "96": "23"
        },
        "22": {
            "119": "5",
            "158": "5",
            "167": "21"
        },
        "23": {
            "215": "21",
            "49": "21",
            "54": "21",
            "69": "21"
        },
        "24": {
            "106": "18",
            "11": "5",
            "144": "18",
            "30": "18"
        },
        "25": {
            "110": "19",
            "154": "26",
            "59": "19",
            "91": "26"
        },
        "26": {
            "135": "26",
            "163": "26",
            "198": "26",
            "240": "26"
        },
        "5": {
            "178": "19"
        },
        "7": {
            "115": "5",
            "125": "5"
        },
        "8": {
            "172": "21",
            "18": "21"
        },
        "9": {
            "226": "23",
            "78": "23"
        }
    },
    "33": {
        "10": {
            "5": "25",
            "65": "25"
        },
        "11": {
            "220": "11",
            "248": "11"
        },
        "12": {
            "150": "17",
            "258": "17"
        },
        "13": {
            "183": "9",
            "253": "9"
        },
        "14": {
            "140": "9",
            "236": "9"
        },
        "15": {
            "232": "17",
            "25": "17"
        },
        "16": {
            "244": "9"
        },
        "17": {
            "194": "9",
            "210": "9",
            "83": "9"
        },
        "18": {
            "131": "20",
            "188": "20",
            "45": "20"
        },
        "19": {
            "100": "25",
            "74": "25"
        },
        "20": {
            "203": "25",
            "36": "25",
            "41": "25"
        },
        "21": {
            "96": "11"
        },
        "22": {
            "119": "9",
            "158": "9",
            "167": "9"
        },
        "23": {
            "215": "25",
            "49": "25",
            "54": "25",
            "69": "25"
        },
        "24": {
            "106": "17",
            "11": "17",
            "144": "17",
            "30": "17"
        },
        "25": {
            "110": "20",
            "154": "20",
            "59": "20",
            "91": "20"
        },
        "26": {
            "135": "20",
            "163": "20",
            "198": "20",
            "240": "20"
        },
        "5": {
            "178": "17"
        },
        "7": {
            "115": "17",
            "125": "17"
        },
        "8": {
            "172": "25",
            "18": "25"
        },
        "9": {
            "226": "11",
            "78": "11"
        }
    },
    "34": {
        "10": {
            "65": "7",
            "70": "6"
        },
        "11": {
            "159": "7",
            "248": "7"
        },
        "12": {
            "150": "0",
            "258": "8"
        },
        "13": {
            "183": "8",
            "253": "8"
        },
        "14": {
            "140": "24",
            "236": "24"
        },
        "15": {
            "232": "1"
        },
        "16": {
            "12": "7",
            "244": "7"
        },
        "17": {
            "194": "24",
            "210": "24",
            "59": "24"
        },
        "18": {
            "131": "1",
            "188": "1",
            "45": "16"
        },
        "19": {
            "199": "24",
            "221": "24",
            "75": "8"
        },
        "20": {
            "111": "24",
            "26": "16",
            "41": "16"
        },
        "21": {
            "101": "1",
            "126": "29",
            "96": "29"
        },
        "22": {
            "119": "0",
            "167": "29",
            "37": "0"
        },
        "23": {
            "204": "29",
            "49": "29",
            "5": "29"
        },
        "24": {
            "106": "29",
            "19": "1",
            "30": "29",
            "55": "29"
        },
        "25": {
            "154": "16",
            "173": "16",
            "216": "1",
            "91": "16"
        },
        "26": {
            "135": "0",
            "145": "16",
            "163": "0",
            "240": "16"
        },
        "5": {
            "178": "6"
        },
        "7": {
            "115": "6",
            "84": "6"
        },
        "9": {
            "226": "29",
            "78": "29"
        }
    },
    "35": {
        "10": {
            "65": "10",
            "70": "10"
        },
        "11": {
            "159": "2",
            "248": "2"
        },
        "12": {
            "150": "27",
            "258": "27"
        },
        "13": {
            "183": "12",
            "253": "12"
        },
        "14": {
            "140": "15",
            "236": "15"
        },
        "15": {
            "232": "5"
        },
        "16": {
            "12": "5",
            "244": "5"
        },
        "17": {
            "194": "27",
            "210": "27",
            "59": "5"
        },
        "18": {
            "131": "10",
            "188": "10",
            "45": "10"
        },
        "19": {
            "199": "15",
            "221": "27",
            "75": "15"
        },
        "20": {
            "111": "3",
            "26": "3",
            "41": "3"
        },
        "21": {
            "101": "10",
            "126": "30",
            "96": "10"
        },
        "22": {
            "119": "2",
            "167": "2",
            "37": "2"
        },
        "23": {
            "204": "30",
            "49": "3",
            "5": "3"
        },
        "24": {
            "106": "30",
            "19": "30",
            "30": "30",
            "55": "30"
        },
        "25": {
            "154": "2",
            "173": "12",
            "216": "30",
            "91": "2"
        },
        "26": {
            "135": "3",
            "145": "15",
            "163": "30",
            "240": "3"
        },
        "5": {
            "178": "12"
        },
        "7": {
            "115": "12",
            "84": "12"
        },
        "9": {
            "226": "27",
            "78": "27"
        }
    },
    "36": {
        "10": {
            "65": "13",
            "70": "13"
        },
        "11": {
            "159": "13",
            "248": "13"
        },
        "12": {
            "150": "26",
            "258": "26"
        },
        "13": {
            "183": "9",
            "253": "9"
        },
        "14": {
            "140": "9",
            "236": "9"
        },
        "15": {
            "232": "26"
        },
        "16": {
            "12": "14",
            "244": "14"
        },
        "17": {
            "194": "21",
            "210": "21",
            "59": "21"
        },
        "18": {
            "131": "14",
            "188": "14",
            "45": "14"
        },
        "19": {
            "199": "26",
            "221": "26",
            "75": "26"
        },
        "20": {
            "111": "26",
            "26": "26",
            "41": "26"
        },
        "21": {
            "101": "14",
            "126": "14",
            "96": "14"
        },
        "22": {
            "119": "9",
            "167": "9",
            "37": "9"
        },
        "23": {
            "204": "14",
            "49": "14",
            "5": "14"
        },
        "24": {
            "106": "21",
            "19": "21",
            "30": "21",
            "55": "21"
        },
        "25": {
            "154": "9",
            "173": "9",
            "216": "9",
            "91": "9"
        },
        "26": {
            "135": "13",
            "145": "13",
            "163": "13",
            "240": "13"
        },
        "5": {
            "178": "13"
        },
        "7": {
            "115": "21",
            "84": "21"
        },
        "9": {
            "226": "21",
            "78": "21"
        }
    },
    "37": {
        "10": {
            "13": "29",
            "70": "1"
        },
        "11": {
            "141": "7"
        },
        "12": {
            "159": "7",
            "237": "0"
        },
        "13": {
            "120": "29",
            "249": "29"
        },
        "14": {
            "132": "7",
            "259": "24"
        },
        "15": {
            "164": "1",
            "232": "1"
        },
        "16": {
            "205": "4",
            "244": "23"
        },
        "17": {
            "194": "23",
            "66": "23"
        },
        "18": {
            "189": "23",
            "45": "23"
        },
        "19": {
            "221": "18",
            "31": "1",
            "75": "4"
        },
        "20": {
            "102": "18",
            "111": "18",
            "26": "18"
        },
        "21": {
            "126": "4",
            "136": "24",
            "96": "24"
        },
        "22": {
            "167": "29",
            "179": "29",
            "37": "29"
        },
        "23": {
            "184": "23",
            "49": "23",
            "5": "23",
            "60": "23"
        },
        "24": {
            "106": "18",
            "19": "18",
            "211": "18",
            "55": "18"
        },
        "25": {
            "173": "4",
            "200": "29",
            "216": "29",
            "91": "4"
        },
        "26": {
            "145": "24",
            "151": "24",
            "155": "24",
            "240": "24"
        },
        "7": {
            "115": "7",
            "84": "7"
        },
        "8": {
            "254": "0",
            "41": "7"
        },
        "9": {
            "226": "0",
            "78": "29"
        }
    },
    "38": {
        "10": {
            "13": "12",
            "70": "12"
        },
        "11": {
            "141": "20"
        },
        "12": {
            "159": "16",
            "237": "16"
        },
        "13": {
            "120": "16",
            "249": "16"
        },
        "14": {
            "132": "27",
            "259": "27"
        },
        "15": {
            "164": "10",
            "232": "10"
        },
        "16": {
            "205": "5",
            "244": "5"
        },
        "17": {
            "194": "20",
            "66": "20"
        },
        "18": {
            "189": "6",
            "45": "6"
        },
        "19": {
            "221": "28",
            "31": "28",
            "75": "27"
        },
        "20": {
            "102": "28",
            "111": "28",
            "26": "28"
        },
        "21": {
            "126": "6",
            "136": "6",
            "96": "6"
        },
        "22": {
            "167": "6",
            "179": "6",
            "37": "12"
        },
        "23": {
            "184": "10",
            "49": "6",
            "5": "27",
            "60": "6"
        },
        "24": {
            "106": "12",
            "19": "12",
            "211": "12",
            "55": "12"
        },
        "25": {
            "173": "28",
            "200": "28",
            "216": "28",
            "91": "28"
        },
        "26": {
            "145": "16",
            "151": "16",
            "155": "20",
            "240": "20"
        },
        "7": {
            "115": "28",
            "84": "10"
        },
        "8": {
            "254": "5",
            "41": "5"
        },
        "9": {
            "226": "27",
            "78": "27"
        }
    },
    "39": {
        "10": {
            "13": "3",
            "70": "3"
        },
        "11": {
            "141": "3"
        },
        "12": {
            "159": "15",
            "237": "15"
        },
        "13": {
            "120": "2",
            "249": "3"
        },
        "14": {
            "132": "26",
            "259": "26"
        },
        "15": {
            "164": "3",
            "232": "26"
        },
        "16": {
            "205": "2",
            "244": "2"
        },
        "17": {
            "194": "21",
            "66": "21"
        },
        "18": {
            "189": "21",
            "45": "21"
        },
        "19": {
            "221": "15",
            "31": "15",
            "75": "15"
        },
        "20": {
            "102": "26",
            "111": "26",
            "26": "26"
        },
        "21": {
            "126": "15",
            "136": "15",
            "96": "15"
        },
        "22": {
            "167": "15",
            "179": "15",
            "37": "15"
        },
        "23": {
            "184": "26",
            "49": "26",
            "5": "26",
            "60": "26"
        },
        "24": {
            "106": "21",
            "19": "21",
            "211": "21",
            "55": "21"
        },
        "25": {
            "173": "26",
            "200": "26",
            "216": "26",
            "91": "26"
        },
        "26": {
            "145": "2",
            "151": "3",
            "155": "3",
            "240": "2"
        },
        "7": {
            "115": "21",
            "84": "21"
        },
        "8": {
            "254": "3",
            "41": "2"
        },
        "9": {
            "226": "21",
            "78": "21"
        }
    },
    "40": {
        "10": {
            "14": "30",
            "97": "1"
        },
        "11": {
            "127": "18",
            "141": "18"
        },
        "12": {
            "159": "18",
            "237": "18"
        },
        "13": {
            "120": "13",
            "245": "13"
        },
        "14": {
            "168": "1",
            "71": "1"
        },
        "15": {
            "164": "18",
            "19": "18"
        },
        "16": {
            "205": "0"
        },
        "17": {
            "116": "7",
            "50": "7",
            "66": "4"
        },
        "18": {
            "189": "7",
            "227": "13",
            "45": "13"
        },
        "19": {
            "31": "4",
            "75": "4",
            "92": "4"
        },
        "20": {
            "102": "25",
            "111": "25",
            "26": "25"
        },
        "21": {
            "136": "25",
            "260": "25",
            "42": "25"
        },
        "22": {
            "179": "13",
            "37": "13",
            "85": "13"
        },
        "23": {
            "132": "25",
            "5": "25",
            "60": "25",
            "78": "25"
        },
        "24": {
            "106": "7",
            "146": "7",
            "211": "7",
            "55": "7"
        },
        "25": {
            "173": "18",
            "200": "18",
            "216": "0",
            "233": "30"
        },
        "26": {
            "151": "25",
            "155": "25",
            "185": "4",
            "240": "4"
        },
        "8": {
            "250": "0",
            "254": "0"
        },
        "9": {
            "195": "30",
            "222": "30"
        }
    },
    "41": {
        "10": {
            "14": "20",
            "97": "20"
        },
        "11": {
            "127": "17",
            "141": "20"
        },
        "12": {
            "159": "19",
            "237": "23"
        },
        "13": {
            "120": "19",
            "245": "19"
        },
        "14": {
            "168": "19",
            "71": "22"
        },
        "15": {
            "164": "22",
            "19": "22"
        },
        "16": {
            "205": "27"
        },
        "17": {
            "116": "8",
            "50": "17",
            "66": "8"
        },
        "18": {
            "189": "20",
            "227": "20",
            "45": "20"
        },
        "19": {
            "31": "29",
            "75": "29",
            "92": "29"
        },
        "20": {
            "102": "27",
            "111": "27",
            "26": "27"
        },
        "21": {
            "136": "29",
            "260": "29",
            "42": "29"
        },
        "22": {
            "179": "27",
            "37": "27",
            "85": "27"
        },
        "23": {
            "132": "23",
            "5": "23",
            "60": "23",
            "78": "8"
        },
        "24": {
            "106": "29",
            "146": "29",
            "211": "29",
            "55": "29"
        },
        "25": {
            "173": "8",
            "200": "29",
            "216": "8",
            "233": "8"
        },
        "26": {
            "151": "23",
            "155": "23",
            "185": "8",
            "240": "23"
        },
        "8": {
            "250": "17",
            "254": "17"
        },
        "9": {
            "195": "22",
            "222": "27"
        }
    },
    "42": {
        "10": {
            "14": "15",
            "97": "15"
        },
        "11": {
            "127": "9",
            "141": "9"
        },
        "12": {
            "159": "15",
            "237": "15"
        },
        "13": {
            "120": "28",
            "245": "28"
        },
        "14": {
            "168": "28",
            "71": "28"
        },
        "15": {
            "164": "9",
            "19": "9"
        },
        "16": {
            "205": "9"
        },
        "17": {
            "116": "28",
            "50": "28",
            "66": "28"
        },
        "18": {
            "189": "9",
            "227": "9",
            "45": "9"
        },
        "19": {
            "31": "15",
            "75": "15",
            "92": "15"
        },
        "20": {
            "102": "11",
            "111": "11",
            "26": "11"
        },
        "21": {
            "136": "15",
            "260": "15",
            "42": "15"
        },
        "22": {
            "179": "10",
            "37": "10",
            "85": "10"
        },
        "23": {
            "132": "28",
            "5": "28",
            "60": "28",
            "78": "28"
        },
        "24": {
            "106": "11",
            "146": "11",
            "211": "11",
            "55": "11"
        },
        "25": {
            "173": "9",
            "200": "9",
            "216": "9",
            "233": "9"
        },
        "26": {
            "151": "10",
            "155": "10",
            "185": "10",
            "240": "10"
        },
        "8": {
            "250": "11",
            "254": "11"
        },
        "9": {
            "195": "10",
            "222": "10"
        }
    },
    "_comments": "Cost: 9404.923872\n\"cc0\": 330.000000, \"cc1\": 478.000000, \"cc2\": 70.000000, \"cc3\": 325.000000, \"cc4\": 1761.000000, \"cc5\": 705.000000, \"cc6\": 1030.000000, \"cc7\": 78.800077, \"cc8\": 593.166627, \"cc9\": 2194.000000, \"cc10\": 807.259987, \"cc11\": 1032.697181, Sum of cost components9404.923872 Time: 98.301645s\n"
}